tihi/__init__.py
tihi/app.py
tihi/wizard.py
tihi/icons/128.png
tihi/icons/16.png
tihi/icons/256.png
tihi/icons/32.png
tihi/icons/64.png
tihi/tests/qt/test_baseline_page.py
tihi/tests/qt/test_distribution_page.py
tihi/tests/qt/test_interpolation_page.py
tihi/tests/qt/test_peak_detection_page.py
tihi/tests/utils/test_baseline_correction.py
tihi/tests/utils/test_distributions.py
tihi/tests/utils/test_interpolate.py
tihi/tests/utils/test_peaks.py
tihi/tihi_utils/__init__.py
tihi/tihi_utils/baseline_corrector.py
tihi/tihi_utils/distributions.py
tihi/tihi_utils/interpolate.py
tihi/tihi_utils/peak_detection.py
tihi/tihi_wizardPages/__init__.py
tihi/tihi_wizardPages/baselinePage.py
tihi/tihi_wizardPages/distributionPage.py
tihi/tihi_wizardPages/interpolatePage.py
tihi/tihi_wizardPages/peak_detectionPage.py
Tihi_spectral_fitter-0.0.4.dist-info/LICENSE
Tihi_spectral_fitter-0.0.4.dist-info/METADATA
Tihi_spectral_fitter-0.0.4.dist-info/WHEEL
Tihi_spectral_fitter-0.0.4.dist-info/entry_points.txt
Tihi_spectral_fitter-0.0.4.dist-info/top_level.txt
Tihi_spectral_fitter-0.0.4.dist-info/RECORD
