Metadata-Version: 2.1
Name: Tihi_spectral_fitter
Version: 0.0.4
Summary: A peak identification and signal decomposition tools for chemical signals
Author: Kyunghoon HAN
Author-email: Kyunghoon Han <kyunghoon.h@gmail.com>
Project-URL: Homepage, https://github.com/kyunghoon-han/tihi
Project-URL: Issues, https://github.com/kyunghoon-han/tihi/issues
Classifier: Programming Language :: Python :: 3
Classifier: License :: OSI Approved :: MIT License
Classifier: Operating System :: OS Independent
Requires-Python: >=3.8
License-File: LICENSE
